digit/__init__.py
digit/base_data.py
digit/child_base_data.py
digit/core.py
digit/data.py
digit/download.py
digit/info.json
digit/info.py
digit/query.py
digit/scripts.py
digit/setting.py
ir_digit-1.1.3.dist-info/LICENSE
ir_digit-1.1.3.dist-info/METADATA
ir_digit-1.1.3.dist-info/WHEEL
ir_digit-1.1.3.dist-info/entry_points.txt
ir_digit-1.1.3.dist-info/top_level.txt
ir_digit-1.1.3.dist-info/RECORD
