Metadata-Version: 2.1
Name: ir-digit
Version: 1.1.3
Summary: digit package
Home-page: https://master--ir-digit-redocs.netlify.app/
Author: FKLiu
Author-email: fkliu001@outlook.com
Classifier: Programming Language :: Python :: 3
Classifier: License :: OSI Approved :: MIT License
Classifier: Operating System :: OS Independent
Requires-Python: >=3.6
License-File: LICENSE
Requires-Dist: gitpython
Requires-Dist: numpy
Requires-Dist: pandas
Requires-Dist: matplotlib
Requires-Dist: seaborn
Requires-Dist: jieba
Requires-Dist: requests
